djaploy/__init__.py
djaploy/artifact.py
djaploy/certificates.py
djaploy/config.py
djaploy/deploy.py
djaploy/utils.py
djaploy/version.py
djaploy/bin/__init__.py
djaploy/bin/django_pyinfra.py
djaploy/management/__init__.py
djaploy/management/utils.py
djaploy/management/commands/__init__.py
djaploy/management/commands/configureserver.py
djaploy/management/commands/deploy.py
djaploy/management/commands/sync_certs.py
djaploy/management/commands/update_certs.py
djaploy/management/commands/verify.py
djaploy/modules/__init__.py
djaploy/modules/base.py
djaploy/modules/cert_renewal.py
djaploy/modules/core.py
djaploy/modules/litestream.py
djaploy/modules/loader.py
djaploy/modules/nginx.py
djaploy/modules/rclone.py
djaploy/modules/sync_certs.py
djaploy/modules/systemd.py
djaploy/modules/tailscale.py
djaploy-0.3.0.dist-info/licenses/LICENSE
djaploy-0.3.0.dist-info/METADATA
djaploy-0.3.0.dist-info/WHEEL
djaploy-0.3.0.dist-info/entry_points.txt
djaploy-0.3.0.dist-info/top_level.txt
djaploy-0.3.0.dist-info/RECORD
