Metadata-Version: 2.4
Name: djaploy
Version: 0.3.0
Summary: Modular Django deployment system based on pyinfra
Author-email: Johanna Mae Dimayuga <johanna@techco.fi>
License: MIT License
Project-URL: Homepage, https://github.com/techco-fi/djaploy
Project-URL: Repository, https://github.com/techco-fi/djaploy
Project-URL: Issues, https://github.com/techco-fi/djaploy/issues
Project-URL: Documentation, https://github.com/techco-fi/djaploy#readme
Keywords: django,deployment,pyinfra,automation,infrastructure
Classifier: Development Status :: 3 - Alpha
Classifier: Environment :: Console
Classifier: Framework :: Django
Classifier: Framework :: Django :: 3.2
Classifier: Framework :: Django :: 4.0
Classifier: Framework :: Django :: 4.1
Classifier: Framework :: Django :: 4.2
Classifier: Framework :: Django :: 5.0
Classifier: Intended Audience :: Developers
Classifier: License :: OSI Approved :: MIT License
Classifier: Operating System :: OS Independent
Classifier: Programming Language :: Python :: 3
Classifier: Programming Language :: Python :: 3.8
Classifier: Programming Language :: Python :: 3.9
Classifier: Programming Language :: Python :: 3.10
Classifier: Programming Language :: Python :: 3.11
Classifier: Programming Language :: Python :: 3.12
Classifier: Topic :: Software Development :: Build Tools
Classifier: Topic :: System :: Installation/Setup
Classifier: Topic :: System :: Systems Administration
Requires-Python: >=3.9
License-File: LICENSE
Requires-Dist: pyinfra<3.5,>=3.4
Requires-Dist: django>=3.2
Provides-Extra: certificates
Requires-Dist: certbot>=2.0; extra == "certificates"
Provides-Extra: bunny
Requires-Dist: certbot-dns-bunny<=0.0.9; extra == "bunny"
Dynamic: license-file
